README.rst
setup.py
pypbs/__init__.py
pypbs/pbsstatus.py
pypbs/pbsxml.py
pypbs/qpeek.py
pypbs/qstat.py
pypbs/util.py
pypbs.egg-info/PKG-INFO
pypbs.egg-info/SOURCES.txt
pypbs.egg-info/dependency_links.txt
pypbs.egg-info/entry_points.txt
pypbs.egg-info/top_level.txt
tests/__init__.py
tests/test_pbsstatus.py
tests/test_pbsxml.py
tests/test_qpeek.py
tests/test_qstat.py
tests/test_util.py