Metadata-Version: 1.0
Name: pypbs
Version: 0.2.0.dev0
Summary: API-ish for pbs
Home-page: UNKNOWN
Author: Tyghe Vallard, Michael panciera
Author-email: vallardt@gmail.com, michael.panciera.work@gmail.com
License: GPLv2
Keywords: torque,pbs
Platform: UNKNOWN
